Metadata-Version: 1.0
Name: joke-cli
Version: 0.1.0
Summary: CLI that fetches and prints random jokes
Home-page: https://github.com/drewtadams/joke_apis
Author: Drew Adams
Author-email: drew@drewtadams.com
License: MIT
Keywords: random,jokes
Platform: UNKNOWN
